<?xml version="1.0" encoding="utf-8"?>
<root id="50272">
  <origen>
    <productor>Agencia Estatal de Meteorología - AEMET. Gobierno de España</productor>
    <web>http://www.aemet.es</web>
    <enlace>http://www.aemet.es/es/eltiempo/prediccion/municipios/utebo-id50272</enlace>
    <language>es</language>
    <copyright>© AEMET. Autorizado el uso de la información y su reproducción citando a AEMET como autora de la misma.</copyright>
    <nota_legal>http://www.aemet.es/es/nota_legal</nota_legal>
  </origen>
  <elaborado>2018-04-20T12:44:02</elaborado>
  <nombre>Utebo</nombre>
  <provincia>Zaragoza</provincia>
  <prediccion>
    <dia fecha="2018-04-20">
      <prob_precipitacion periodo="18-24">0</prob_precipitacion>
      <cota_nieve_prov periodo="18-24"/>
      <estado_cielo periodo="18-24" descripcion="Despejado">11</estado_cielo>
      <viento periodo="18-24">
        <direccion>E</direccion>
        <velocidad>10</velocidad>
      </viento>
      <racha_max periodo="18-24"/>
      <temperatura>
        <maxima>25</maxima>
        <minima>10</minima>
        <dato hora="24">14</dato>
      </temperatura>
      <sens_termica>
        <maxima>25</maxima>
        <minima>10</minima>
      </sens_termica>
      <humedad_relativa>
        <maxima>95</maxima>
        <minima>40</minima>
      </humedad_relativa>
      <uv_max>6</uv_max>
    </dia>
    <dia fecha="2018-04-21">
      <prob_precipitacion periodo="00-06">0</prob_precipitacion>
      <prob_precipitacion periodo="06-12">0</prob_precipitacion>
      <prob_precipitacion periodo="12-18">0</prob_precipitacion>
      <prob_precipitacion periodo="18-24">0</prob_precipitacion>
      <cota_nieve_prov periodo="00-06"/>
      <cota_nieve_prov periodo="06-12"/>
      <cota_nieve_prov periodo="12-18"/>
      <cota_nieve_prov periodo="18-24"/>
      <estado_cielo periodo="00-06" descripcion="Despejado">11n</estado_cielo>
      <estado_cielo periodo="06-12" descripcion="Despejado">11</estado_cielo>
      <estado_cielo periodo="12-18" descripcion="Despejado">11</estado_cielo>
      <estado_cielo periodo="18-24" descripcion="Despejado">11</estado_cielo>
      <viento periodo="00-06">
        <direccion>C</direccion>
        <velocidad>0</velocidad>
      </viento>
      <viento periodo="06-12">
        <direccion>SE</direccion>
        <velocidad>15</velocidad>
      </viento>
      <viento periodo="12-18">
        <direccion>SE</direccion>
        <velocidad>15</velocidad>
      </viento>
      <viento periodo="18-24">
        <direccion>E</direccion>
        <velocidad>10</velocidad>
      </viento>
      <racha_max periodo="00-06"/>
      <racha_max periodo="06-12"/>
      <racha_max periodo="12-18"/>
      <racha_max periodo="18-24"/>
      <temperatura>
        <maxima>26</maxima>
        <minima>10</minima>
        <dato hora="06">10</dato>
        <dato hora="12">24</dato>
        <dato hora="18">24</dato>
        <dato hora="24">15</dato>
      </temperatura>
      <sens_termica>
        <maxima>26</maxima>
        <minima>10</minima>
      </sens_termica>
      <humedad_relativa>
        <maxima>95</maxima>
        <minima>35</minima>
      </humedad_relativa>
      <uv_max>6</uv_max>
    </dia>
    <dia fecha="2018-04-22">
      <prob_precipitacion periodo="00-12">0</prob_precipitacion>
      <prob_precipitacion periodo="12-24">5</prob_precipitacion>
      <cota_nieve_prov periodo="00-12"/>
      <cota_nieve_prov periodo="12-24"/>
      <estado_cielo periodo="00-12" descripcion="Nubes altas">17</estado_cielo>
      <estado_cielo periodo="12-24" descripcion="Intervalos nubosos">13</estado_cielo>
      <viento periodo="00-12">
        <direccion>E</direccion>
        <velocidad>10</velocidad>
      </viento>
      <viento periodo="12-24">
        <direccion>E</direccion>
        <velocidad>10</velocidad>
      </viento>
      <racha_max periodo="00-12"/>
      <racha_max periodo="12-24"/>
      <temperatura>
        <maxima>27</maxima>
        <minima>12</minima>
        <dato hora="12"></dato>
        <dato hora="24"></dato>
      </temperatura>
      <sens_termica>
        <maxima>27</maxima>
        <minima>12</minima>
      </sens_termica>
      <humedad_relativa>
        <maxima>75</maxima>
        <minima>30</minima>
      </humedad_relativa>
      <uv_max>6</uv_max>
    </dia>
    <dia fecha="2018-04-23">
      <prob_precipitacion periodo="00-12">0</prob_precipitacion>
      <prob_precipitacion periodo="12-24">0</prob_precipitacion>
      <cota_nieve_prov periodo="00-12"/>
      <cota_nieve_prov periodo="12-24"/>
      <estado_cielo periodo="00-12" descripcion="Nubes altas">17</estado_cielo>
      <estado_cielo periodo="12-24" descripcion="Nubes altas">17</estado_cielo>
      <viento periodo="00-12">
        <direccion>E</direccion>
        <velocidad>5</velocidad>
      </viento>
      <viento periodo="12-24">
        <direccion>C</direccion>
        <velocidad>0</velocidad>
      </viento>
      <racha_max periodo="00-12"/>
      <racha_max periodo="12-24"/>
      <temperatura>
        <maxima>28</maxima>
        <minima>12</minima>
        <dato hora="12"></dato>
        <dato hora="24"></dato>
      </temperatura>
      <sens_termica>
        <maxima>30</maxima>
        <minima>12</minima>
      </sens_termica>
      <humedad_relativa>
        <maxima>85</maxima>
        <minima>35</minima>
      </humedad_relativa>
      <uv_max>6</uv_max>
    </dia>
    <dia fecha="2018-04-24">
      <prob_precipitacion>45</prob_precipitacion>
      <cota_nieve_prov/>
      <estado_cielo descripcion="Poco nuboso">12</estado_cielo>
      <viento>
        <direccion>E</direccion>
        <velocidad>10</velocidad>
      </viento>
      <racha_max/>
      <temperatura>
        <maxima>30</maxima>
        <minima>13</minima>
        <dato hora="24"></dato>
      </temperatura>
      <sens_termica>
        <maxima>30</maxima>
        <minima>13</minima>
      </sens_termica>
      <humedad_relativa>
        <maxima>80</maxima>
        <minima>30</minima>
      </humedad_relativa>
      <uv_max>7</uv_max>
    </dia>
    <dia fecha="2018-04-25">
      <prob_precipitacion>25</prob_precipitacion>
      <cota_nieve_prov/>
      <estado_cielo descripcion="Intervalos nubosos">13</estado_cielo>
      <viento>
        <direccion>E</direccion>
        <velocidad>10</velocidad>
      </viento>
      <racha_max/>
      <temperatura>
        <maxima>29</maxima>
        <minima>13</minima>
        <dato hora="24"></dato>
      </temperatura>
      <sens_termica>
        <maxima>29</maxima>
        <minima>13</minima>
      </sens_termica>
      <humedad_relativa>
        <maxima>60</maxima>
        <minima>25</minima>
      </humedad_relativa>
    </dia>
    <dia fecha="2018-04-26">
      <prob_precipitacion>70</prob_precipitacion>
      <cota_nieve_prov/>
      <estado_cielo descripcion="Muy nuboso con lluvia">25</estado_cielo>
      <viento>
        <direccion>NO</direccion>
        <velocidad>10</velocidad>
      </viento>
      <racha_max>60</racha_max>
      <temperatura>
        <maxima>23</maxima>
        <minima>12</minima>
        <dato hora="24"></dato>
      </temperatura>
      <sens_termica>
        <maxima>23</maxima>
        <minima>12</minima>
      </sens_termica>
      <humedad_relativa>
        <maxima>65</maxima>
        <minima>40</minima>
      </humedad_relativa>
    </dia>
  </prediccion>
</root>